llama_index/readers/remote/__init__.py
llama_index/readers/remote/base.py
llama_index_readers_remote-0.4.1.dist-info/METADATA
llama_index_readers_remote-0.4.1.dist-info/WHEEL
llama_index_readers_remote-0.4.1.dist-info/licenses/LICENSE
llama_index_readers_remote-0.4.1.dist-info/RECORD
