Metadata-Version: 2.4
Name: llama-index-readers-remote
Version: 0.4.1
Summary: llama-index readers remote integration
Author-email: Your Name <you@example.com>
Maintainer: thejessezhang
License-Expression: MIT
License-File: LICENSE
Keywords: gutenberg,hosted,url
Requires-Python: <4.0,>=3.9
Requires-Dist: llama-index-core<0.15,>=0.13.0
Requires-Dist: llama-index-readers-youtube-transcript<0.5,>=0.4.0
